omnipy/__init__.py
omnipy/_dynamic_all.py
omnipy/components/__init__.py
omnipy/components/_fairtracks/__init__.py
omnipy/components/_fairtracks/create_filter.py
omnipy/components/_fairtracks/functions.py
omnipy/components/_fairtracks/get_from_filter.py
omnipy/components/_fairtracks/tasks.py
omnipy/components/_frozen/__init__.py
omnipy/components/_frozen/datasets.py
omnipy/components/_frozen/models.py
omnipy/components/_frozen/typedefs.py
omnipy/components/general/__init__.py
omnipy/components/general/models.py
omnipy/components/general/tasks.py
omnipy/components/isa/__init__.py
omnipy/components/isa/datasets.py
omnipy/components/isa/flows.py
omnipy/components/isa/models/__init__.py
omnipy/components/isa/models/assay_schema.py
omnipy/components/isa/models/comment_schema.py
omnipy/components/isa/models/data_schema.py
omnipy/components/isa/models/factor_schema.py
omnipy/components/isa/models/factor_value_schema.py
omnipy/components/isa/models/investigation_schema.py
omnipy/components/isa/models/material_attribute_schema.py
omnipy/components/isa/models/material_attribute_value_schema.py
omnipy/components/isa/models/material_schema.py
omnipy/components/isa/models/ontology_annotation_schema.py
omnipy/components/isa/models/ontology_source_reference_schema.py
omnipy/components/isa/models/organization_schema.py
omnipy/components/isa/models/person_schema.py
omnipy/components/isa/models/process_parameter_value_schema.py
omnipy/components/isa/models/process_schema.py
omnipy/components/isa/models/protocol_parameter_schema.py
omnipy/components/isa/models/protocol_schema.py
omnipy/components/isa/models/publication_schema.py
omnipy/components/isa/models/sample_schema.py
omnipy/components/isa/models/source_schema.py
omnipy/components/isa/models/study_group.py
omnipy/components/isa/models/study_schema.py
omnipy/components/isa/models/validators.py
omnipy/components/json/__init__.py
omnipy/components/json/_functions.py
omnipy/components/json/constants.py
omnipy-0.22.1.dist-info/LICENSE
omnipy-0.22.1.dist-info/METADATA
omnipy-0.22.1.dist-info/WHEEL
omnipy-0.22.1.dist-info/entry_points.txt
omnipy-0.22.1.dist-info/RECORD
