Metadata-Version: 2.3
Name: omnipy
Version: 0.22.1
Summary: Omnipy is a type-driven Python library for data conversion, parsing and wrangling; tool and web service interoperability; and scalable dataflow orchestration
License: Apache License
Keywords: data wrangling,metadata,workflows,etl,research data,prefect,pydantic,FAIR,ontologies,JSON,tabular,type-driven,orchestration,data models,universal
Author: Sveinung Gundersen
Maintainer: Sveinung Gundersen
Requires-Python: >=3.10,<3.14
Classifier: Development Status :: 2 - Pre-Alpha
Classifier: Framework :: Pydantic
Classifier: Intended Audience :: Developers
Classifier: Intended Audience :: Science/Research
Classifier: License :: OSI Approved :: Apache Software License
Classifier: Programming Language :: Python :: 3.10
Classifier: Programming Language :: Python :: 3.11
Classifier: Programming Language :: Python :: 3.12
Classifier: Programming Language :: Python :: 3.13
Classifier: Topic :: Software Development :: Libraries
Requires-Dist: aiohttp (>=3.10.6,<4)
Requires-Dist: aiohttp-retry (>=2.9.0,<3)
Requires-Dist: aiolimiter (>=1.1.0,<2)
Requires-Dist: asyncpg (>=0.30)
Requires-Dist: bitarray (>=3.0.0,<4.0.0)
Requires-Dist: cachebox (>=5.0.1,<6.0.0)
Requires-Dist: chardet (>=5.2.0,<6)
Requires-Dist: compact-json (>=1.8.1,<2.0.0)
Requires-Dist: devtools (>=0.12.2,<1)
Requires-Dist: griffe (<1)
Requires-Dist: humanize (>=4.9.0,<5)
Requires-Dist: inflection (>=0.5.1,<0.6.0)
Requires-Dist: ipython (<8)
Requires-Dist: notebook (>=7.4.5,<8.0.0)
Requires-Dist: numpy (>=2,<3)
Requires-Dist: objsize (>=0.7.0,<1)
Requires-Dist: pandas (>=2.2)
Requires-Dist: pathspec (>=0.12.1,<1)
Requires-Dist: pathvalidate (>=3.3.1,<4.0.0)
Requires-Dist: placeholder (>=1.5.1,<2.0.0)
Requires-Dist: prefect (>=2.13.2,<3)
Requires-Dist: pydantic-core (>=2.24.2,<3)
Requires-Dist: pydantic[email] (<2)
Requires-Dist: pygments (>=2.19.1,<3.0.0)
Requires-Dist: pyreadline (>=2.1,<3.0)
Requires-Dist: python-slugify (>=8.0.4,<9)
Requires-Dist: rich (>=13.9.4,<14.0.0)
Requires-Dist: ruamel-yaml (>=0.18.10,<0.19.0)
Requires-Dist: simple-hexdump (>=0.0.1,<0.0.2)
Requires-Dist: solara-ui (>=1.48.0,<2.0.0)
Requires-Dist: term-background (>=1.0.2,<2.0.0)
Requires-Dist: typing-extensions (>=4.12.2,<5)
Project-URL: Documentation, http://omnipy.readthedocs.io/
Project-URL: Homepage, https://fairtracks.net/fair/#fair-07-transformation
Project-URL: releasenotes, https://omnipy.readthedocs.io/en/latest/release_notes/
Project-URL: source, http://github.com/fairtracks/omnipy
